nab3/__init__.py
nab3/aws.py
nab3/base.py
nab3/mixin.py
nab3/utils.py
nab3/helpers/__init__.py
nab3/helpers/cloud_watch.py
nab3/helpers/ec2.py
nab3/helpers/ecs.py
nab3/service/__init__.py
nab3/service/autoscaling.py
nab3/service/cloudwatch.py
nab3/service/ec2.py
nab3/service/ecs.py
nab3/service/elasticache.py
nab3/service/kafka.py
nab3/service/load_balancer.py
nab3/service/pricing.py
nab3/service/rds.py
nab3-0.2.2.dist-info/LICENSE
nab3-0.2.2.dist-info/METADATA
nab3-0.2.2.dist-info/WHEEL
nab3-0.2.2.dist-info/top_level.txt
nab3-0.2.2.dist-info/RECORD
